setup.py
jkpip/__init__.py
jkpip/source_change.py
jkpip.egg-info/PKG-INFO
jkpip.egg-info/SOURCES.txt
jkpip.egg-info/dependency_links.txt
jkpip.egg-info/top_level.txt