Metadata-Version: 1.0
Name: jkpip
Version: 0.1.4
Summary: pip source tool
Home-page: https://github.com/a5225662/jkpipsource
Author: jackief
Author-email: jackief@foxmail.com
License: MIT Licence
Keywords: pip,source,tool
Platform: any
